LICENSE
README.md
setup.py
sidle/__init__.py
sidle/_sidle.py
sidle/enc.py
sidle/errors.py
sidle/utils.py
sidle.egg-info/PKG-INFO
sidle.egg-info/SOURCES.txt
sidle.egg-info/dependency_links.txt
sidle.egg-info/requires.txt
sidle.egg-info/top_level.txt