Metadata-Version: 2.1
Name: sidle
Version: 0.0.3
Summary:  A simple data encryption with password for Python 3.
Home-page: UNKNOWN
Author: Zenqi
License: MIT
Platform: UNKNOWN
License-File: LICENSE
